BaiduGrabber-1.1.5.dist-info/DESCRIPTION.rst
BaiduGrabber-1.1.5.dist-info/METADATA
BaiduGrabber-1.1.5.dist-info/RECORD
BaiduGrabber-1.1.5.dist-info/WHEEL
BaiduGrabber-1.1.5.dist-info/entry_points.txt
BaiduGrabber-1.1.5.dist-info/metadata.json
BaiduGrabber-1.1.5.dist-info/top_level.txt
baidugrabber/__init__.py
baidugrabber/__main__.py
baidugrabber/munch.py
baidugrabber/resources.py
