Metadata-Version: 2.0
Name: BaiduGrabber
Version: 1.1.5
Summary: Convert and save Baidu Docs to PDF
Home-page: https://github.com/ozmartian/baidu-docs-grabber
Author: Pete Alexandrou
Author-email: pete@ozmartians.com
License: GPLv3+
Keywords: baidu-grabber baidu-docs baidu docs pdf
Platform: UNKNOWN
Classifier: Development Status :: 5 - Production/Stable
Classifier: Environment :: MacOS X :: Cocoa
Classifier: Environment :: Win32 (MS Windows)
Classifier: Environment :: X11 Applications :: Qt
Classifier: Intended Audience :: End Users/Desktop
Classifier: License :: OSI Approved :: GNU General Public License v3 or later (GPLv3+)
Classifier: Natural Language :: English
Classifier: Operating System :: OS Independent
Classifier: Topic :: Internet
Classifier: Programming Language :: Python :: 3 :: Only
